typer_pydantic_config/__init__.py
typer_pydantic_config/click_utils.py
typer_pydantic_config/config_app.py
typer_pydantic_config/constants.py
typer_pydantic_config/context.py
typer_pydantic_config/dict_utils.py
typer_pydantic_config/prompt_utils.py
typer_pydantic_config/pydantic_writer.py
typer_pydantic_config-0.5.0.dist-info/METADATA
typer_pydantic_config-0.5.0.dist-info/WHEEL
typer_pydantic_config-0.5.0.dist-info/licenses/LICENSE
typer_pydantic_config-0.5.0.dist-info/RECORD
