Metadata-Version: 2.4
Name: typer-pydantic-config
Version: 0.5.0
Summary: Use [pydantic](https://docs.pydantic.dev/latest/) to manage persistent config for your [Typer](https://typer.tiangolo.com/) CLI apps!
Project-URL: Homepage, https://github.com/david-fischer/typer-pydantic-config
Project-URL: Repository, https://github.com/david-fischer/typer-pydantic-config.git
Project-URL: Issues, https://github.com/david-fischer/typer-pydantic-config/issues
Project-URL: Changelog, https://github.com/david-fischer/typer-pydantic-config/blob/master/CHANGELOG.md
Author-email: David Fischer <d.fischer.git@posteo.de>
License-Expression: MIT
License-File: LICENSE
Keywords: CLI,config,pydantic,python,typer
Requires-Python: >=3.12
Requires-Dist: platformdirs>=4.3.7
Requires-Dist: pydantic>=2.10.6
Requires-Dist: toml>=0.10.2
Requires-Dist: typer>=0.15.1
